edb_pot-2.1.1.data/data/share/edb-pot/scripts/install_requirements_darwin_x64.sh
edb_pot-2.1.1.data/data/share/edb-pot/scripts/install_requirements_linux_x64.sh
edb_pot-2.1.1.data/scripts/edb-pot
edbpotdeploy/__init__.py
edbpotdeploy/action.py
edbpotdeploy/ansible.py
edbpotdeploy/cli.py
edbpotdeploy/cloud.py
edbpotdeploy/command.py
edbpotdeploy/project.py
edbpotdeploy/specifications.py
edbpotdeploy/system.py
edbpotdeploy/terraform.py
edbpotdeploy/data/ansible/EDB-RA-1.yml
edbpotdeploy/data/ansible/EDB-RA-2.yml
edbpotdeploy/data/ansible/EDB-RA-3.yml
edbpotdeploy/data/ansible/roles/pot_setup/defaults/main.yml
edbpotdeploy/data/ansible/roles/pot_setup/handlers/main.yml
edbpotdeploy/data/ansible/roles/pot_setup/meta/main.yml
edbpotdeploy/data/ansible/roles/pot_setup/tasks/efm_scripts_rules.yml
edbpotdeploy/data/ansible/roles/pot_setup/tasks/main.yml
edbpotdeploy/data/ansible/roles/pot_setup/tasks/os_configure_user.yml
edbpotdeploy/data/ansible/roles/pot_setup/tasks/pem_server_certs.yml
edbpotdeploy/data/ansible/roles/pot_setup/tasks/pem_server_probe_alert.yml
edbpotdeploy/data/ansible/roles/pot_setup/tasks/pg_create_user.yml
edbpotdeploy/data/ansible/roles/pot_setup/tasks/pg_hba_rule.yml
edbpotdeploy/data/ansible/roles/pot_setup/tasks/pg_pot_hba.yml
edbpotdeploy/data/ansible/roles/pot_setup/tasks/pg_pot_scripts.yml
edbpotdeploy/data/ansible/roles/pot_setup/tasks/pg_user_pgpass.yml
edbpotdeploy/data/ansible/roles/pot_setup/tasks/pot_setup.yml
edbpotdeploy/data/ansible/roles/pot_setup/tasks/update_route53.yml
edbpotdeploy/data/ansible/roles/pot_setup/tasks/verify_variables.yml
edbpotdeploy/data/ansible/roles/pot_setup/templates/efm_db_functions.3.10.template
edbpotdeploy/data/ansible/roles/pot_setup/templates/efm_db_functions.4.0.template
edbpotdeploy/data/ansible/roles/pot_setup/templates/efm_db_functions.4.1.template
edbpotdeploy/data/ansible/roles/pot_setup/templates/efm_reconfigure_node.sh.template
edb_pot-2.1.1.dist-info/LICENSE.md
edb_pot-2.1.1.dist-info/METADATA
edb_pot-2.1.1.dist-info/WHEEL
edb_pot-2.1.1.dist-info/top_level.txt
edb_pot-2.1.1.dist-info/RECORD
