Metadata-Version: 2.1
Name: edb-pot
Version: 2.1.1
Summary: Postgres Deployment Scripts are an easy way to deploy PostgreSQL, EDB Postgres Advanced Server, and EDB Tools in the Cloud. 
Home-page: https://github.com/EnterpriseDB/postgres-deployment/
Author: EDB
Author-email: edb-devops@enterprisedb.com
License: BSD
Keywords: postgresql edb epas cli deploy cloud aws azure gcloud
Platform: UNKNOWN
Classifier: Development Status :: 5 - Production/Stable
Classifier: Environment :: Console
Classifier: License :: OSI Approved :: BSD License
Classifier: Programming Language :: Python :: 2.7
Classifier: Programming Language :: Python :: 3
Classifier: Topic :: Database
Requires-Python: >=2.7
License-File: LICENSE.md
Requires-Dist: argcomplete
